jtatistic/__init__.py
jtatistic/dataset.py
jtatisctic-0.0.2.dist-info/METADATA
jtatisctic-0.0.2.dist-info/WHEEL
jtatisctic-0.0.2.dist-info/top_level.txt
jtatisctic-0.0.2.dist-info/RECORD
