Metadata-Version: 2.1
Name: jtatisctic
Version: 0.0.2
Summary: data analysis and statictic tools
Home-page: https://github.com/cavadsalman/jtatistic
Author: Javad Salman
Author-email: aetimpani@yandex.com
License: UNKNOWN
Keywords: python,statistic,dataset
Platform: UNKNOWN
Classifier: Development Status :: 4 - Beta
Classifier: Intended Audience :: Developers
Classifier: Programming Language :: Python :: 3.6
Classifier: Programming Language :: Python :: 3.7
Classifier: Programming Language :: Python :: 3.8
Classifier: Programming Language :: Python :: 3.9
